EDutils/__init__.py
EDutils/convert_pets.sh
EDutils/display.py
EDutils/pets.py
EDutils/pets_ref.sh
EDutils/postprocess.py
EDutils/potential.py
EDutils/rotate_exp.py
EDutils/scattering_factors.py
EDutils/splines.py
EDutils/structure_factor.py
EDutils/utilities.py
EDutils/viewers.py
EDutils/data/abcd.npy
EDutils/data/elec.pkl
EDutils/data/spline_1.txt
EDutils/data/spline_14.txt
EDutils/data/spline_16.txt
EDutils/data/spline_6.txt
EDutils/data/spline_7.txt
EDutils/data/spline_8.txt
EDutils/data/splines.npy
EDutils/data/xray.pkl
EDutilities-0.6.dist-info/LICENSE
EDutilities-0.6.dist-info/METADATA
EDutilities-0.6.dist-info/WHEEL
EDutilities-0.6.dist-info/top_level.txt
EDutilities-0.6.dist-info/RECORD
