Metadata-Version: 2.1
Name: EDutilities
Version: 0.6
Summary: Continuous Electron Diffraction utilities 
Home-page: UNKNOWN
Author: Tarik Ronan Drevon
Author-email: tarik.drevon@stfc.ac.uk
License: UNKNOWN
Platform: UNKNOWN
Classifier: Programming Language :: Python :: 3
Classifier: License :: OSI Approved :: BSD License 
Classifier: Operating System :: POSIX :: Linux 
Requires-Python: >=3.8
Requires-Dist: cbf
Requires-Dist: crystals
Requires-Dist: easygui
Requires-Dist: pickle5
Requires-Dist: tarikDrevonUtils
Requires-Dist: tifffile
